biochatter/__init__.py
biochatter/_image.py
biochatter/_misc.py
biochatter/_stats.py
biochatter/api_agent/__init__.py
biochatter/api_agent/base/__init__.py
biochatter/api_agent/base/agent_abc.py
biochatter/api_agent/base/api_agent.py
biochatter/api_agent/base/formatters.py
biochatter/api_agent/python/__init__.py
biochatter/api_agent/python/anndata_agent.py
biochatter/api_agent/python/autogenerate_model.py
biochatter/api_agent/python/generic_agent.py
biochatter/api_agent/python/scanpy_pl_full.py
biochatter/api_agent/python/scanpy_pl_reduced.py
biochatter/api_agent/python/scanpy_pp_full.py
biochatter/api_agent/python/scanpy_pp_reduced.py
biochatter/api_agent/web/__init__.py
biochatter/api_agent/web/bio_tools.py
biochatter/api_agent/web/blast.py
biochatter/api_agent/web/oncokb.py
biochatter/constants.py
biochatter/database_agent.py
biochatter/kg_langgraph_agent.py
biochatter/langgraph_agent_base.py
biochatter/llm_connect/__init__.py
biochatter/llm_connect/anthropic.py
biochatter/llm_connect/available_models.py
biochatter/llm_connect/azure.py
biochatter/llm_connect/conversation.py
biochatter/llm_connect/gemini.py
biochatter/llm_connect/langchain.py
biochatter/llm_connect/llmlite.py
biochatter/llm_connect/misc.py
biochatter/llm_connect/ollama.py
biochatter/llm_connect/openai.py
biochatter/llm_connect/openrouter.py
biochatter/llm_connect/xinference.py
biochatter/podcast.py
biochatter/prompts.py
biochatter/query_interaction.py
biochatter/rag_agent.py
biochatter/selector_agent.py
biochatter/vectorstore.py
biochatter/vectorstore_agent.py
biochatter-0.14.0.dist-info/METADATA
biochatter-0.14.0.dist-info/WHEEL
biochatter-0.14.0.dist-info/licenses/LICENSE
biochatter-0.14.0.dist-info/RECORD
