Metadata-Version: 2.4
Name: biochatter
Version: 0.14.0
Summary: Backend library for conversational AI in biomedicine
License-Expression: MIT
License-File: LICENSE
Author: Sebastian Lobentanzer
Author-email: sebastian.lobentanzer@gmail.com
Requires-Python: >=3.10,<3.13
Classifier: Development Status :: 3 - Alpha
Classifier: Intended Audience :: Developers
Classifier: Intended Audience :: Science/Research
Classifier: License :: OSI Approved :: MIT License
Classifier: Operating System :: OS Independent
Classifier: Programming Language :: Python
Classifier: Natural Language :: English
Classifier: Topic :: Scientific/Engineering :: Bio-Informatics
Requires-Dist: anthropic (>=0.49.0,<0.50.0)
Requires-Dist: colorcet (>=3.1.0,<4.0.0)
Requires-Dist: cryptography (>=44.0.2,<45.0.0)
Requires-Dist: docstring-parser (>=0.16,<0.17)
Requires-Dist: evaluate (>=0.4.3,<0.5.0)
Requires-Dist: grandalf (>=0.8,<0.9)
Requires-Dist: httpx (>=0.28.1,<0.29.0)
Requires-Dist: importlib-metadata (>=8.6.1,<9.0.0)
Requires-Dist: langchain (>=0.3.20,<0.4.0)
Requires-Dist: langchain-anthropic (>=0.3.10,<0.4.0)
Requires-Dist: langchain-community (>=0.3.19,<0.4.0)
Requires-Dist: langchain-google-genai (>=2.1.0,<3.0.0)
Requires-Dist: langchain-openai (>=0.3.8,<0.4.0)
Requires-Dist: langgraph (>=0.3.11,<0.4.0)
Requires-Dist: litellm (>=1.68.2,<2.0.0)
Requires-Dist: neo4j-utils (>=0.0.12,<0.0.13)
Requires-Dist: nltk (>=3.9.1,<4.0.0)
Requires-Dist: openai (>=1.66.3,<2.0.0)
Requires-Dist: pdf2image (>=1.17.0,<2.0.0)
Requires-Dist: pillow (==10.4.0)
Requires-Dist: pymilvus (>=2.5.5,<3.0.0)
Requires-Dist: pymupdf (>=1.25.4,<2.0.0)
Requires-Dist: redis (>=5.2.1,<6.0.0)
Requires-Dist: retry (>=0.9.2,<0.10.1)
Requires-Dist: rouge-score (>=0.1.2,<0.2.0)
Requires-Dist: rsa (>=4.9,<5.0)
Requires-Dist: seaborn (>=0.13.2,<0.14.0)
Requires-Dist: stringcase (>=1.2.0,<2.0.0)
Requires-Dist: tiktoken (>=0.9.0,<0.10.1)
Requires-Dist: transformers (>=4.49.0,<5.0.0)
Project-URL: Documentation, https://biochatter.org
Project-URL: Homepage, https://biochatter.org
Project-URL: Issues, https://github.com/biocypher/biochatter/issues
Project-URL: Repository, https://github.com/biocypher/biochatter.git
